biomap/__init__.py
biomap/utils/__init__.py
biomap/utils/bioset.py
biomap/utils/ftp.py
biomap/utils/genome.py
biomap/utils/http.py
biomap/utils/table.py
biomap/utils/xml.py
biomap_utils-0.0.51.dist-info/LICENSE
biomap_utils-0.0.51.dist-info/METADATA
biomap_utils-0.0.51.dist-info/WHEEL
biomap_utils-0.0.51.dist-info/top_level.txt
biomap_utils-0.0.51.dist-info/RECORD
